{"FFC_sans_bias60": {"write": {"device_start": -1, "host_queued_start": 1585639629.5166, "device_queued": -1, "device_end": -1, "host_queued_end": 1585639629.520605}, "device": "gpu", "nd_range": {"device_start": 1585639562.6417756, "device_end": 1585639562.642503}, "cmdq": 0, "read": {"device_start": -1, "device_end": -1}}, "FFC_sans_bias4": {"write": {"device_start": -1, "host_queued_start": 1585639629.548404, "device_queued": -1, "device_end": -1, "host_queued_end": 1585639629.560889}, "device": "cpu", "nd_range": {"device_start": 2307403.842613858, "device_end": 2307403.849297259}, "cmdq": 2, "read": {"device_start": -1, "device_end": -1}}, "FFC_sans_bias7": {"write": {"device_start": -1, "host_queued_start": 1585639629.555876, "device_queued": -1, "device_end": -1, "host_queued_end": 1585639629.560889}, "device": "cpu", "nd_range": {"device_start": 2307403.887755304, "device_end": 2307403.903878907}, "cmdq": 0, "read": {"device_start": -1, "device_end": -1}}, "FFC_sans_bias6": {"write": {"device_start": -1, "host_queued_start": 1585639629.55306, "device_queued": -1, "device_end": -1, "host_queued_end": 1585639629.560889}, "device": "cpu", "nd_range": {"device_start": 2307403.865108202, "device_end": 2307403.880570401}, "cmdq": 2, "read": {"device_start": -1, "device_end": -1}}, "FFC_sans_bias1": {"write": {"device_start": -1, "host_queued_start": 1585639629.528947, "device_queued": -1, "device_end": -1, "host_queued_end": 1585639629.560889}, "device": "cpu", "nd_range": {"device_start": 2307403.751052493, "device_end": 2307403.7663881932}, "cmdq": 3, "read": {"device_start": -1, "device_end": -1}}, "FFC_sans_bias0": {"write": {"device_start": -1, "host_queued_start": 1585639629.527755, "device_queued": -1, "device_end": -1, "host_queued_end": 1585639629.560889}, "device": "cpu", "nd_range": {"device_start": 2307403.750561159, "device_end": 2307403.7671049433}, "cmdq": 2, "read": {"device_start": -1, "device_end": -1}}, "FFC_sans_bias2": {"write": {"device_start": -1, "host_queued_start": 1585639629.530147, "device_queued": -1, "device_end": -1, "host_queued_end": 1585639629.560889}, "device": "cpu", "nd_range": {"device_start": 2307403.750532141, "device_end": 2307403.7660382544}, "cmdq": 0, "read": {"device_start": -1, "device_end": -1}}, "FFC_sans_bias61": {"write": {"device_start": 1585639562.6426287, "host_queued_start": 1585639629.518382, "device_queued": 1585639562.6375139, "device_end": 1585639562.6426597, "host_queued_end": 1585639629.520605}, "device": "gpu", "nd_range": {"device_start": 1585639562.6426654, "device_end": 1585639562.643485}, "cmdq": 0, "read": {"device_start": 1585639562.6434891, "device_end": 1585639562.6435144}}, "FFC_sans_bias52": {"write": {"device_start": -1, "host_queued_start": 1585639629.560844, "device_queued": -1, "device_end": -1, "host_queued_end": 1585639629.560889}, "device": "cpu", "nd_range": {"device_start": 2307403.880718855, "device_end": 2307403.9034290724}, "cmdq": 1, "read": {"device_start": -1, "device_end": -1}}, "FFC_sans_bias9": {"write": {"device_start": -1, "host_queued_start": 1585639629.531243, "device_queued": -1, "device_end": -1, "host_queued_end": 1585639629.560889}, "device": "cpu", "nd_range": {"device_start": 2307403.7505318923, "device_end": 2307403.765800844}, "cmdq": 1, "read": {"device_start": -1, "device_end": -1}}, "coalesced_transpose39": {"write": {"device_start": -1, "host_queued_start": 1585639629.547724, "device_queued": -1, "device_end": -1, "host_queued_end": 1585639629.560889}, "device": "cpu", "nd_range": {"device_start": 2307403.8422553153, "device_end": 2307403.8429250363}, "cmdq": 0, "read": {"device_start": -1, "device_end": -1}}, "FFC_sans_bias55": {"write": {"device_start": 1585639562.6362836, "host_queued_start": 1585639629.507297, "device_queued": 1585639562.6361256, "device_end": 1585639562.636316, "host_queued_end": 1585639629.520605}, "device": "gpu", "nd_range": {"device_start": 1585639562.6363192, "device_end": 1585639562.6376896}, "cmdq": 2, "read": {"device_start": -1, "device_end": -1}}, "FFC_sans_bias54": {"write": {"device_start": 1585639562.6361942, "host_queued_start": 1585639629.506204, "device_queued": 1585639562.6361048, "device_end": 1585639562.6362774, "host_queued_end": 1585639629.520605}, "device": "gpu", "nd_range": {"device_start": 1585639562.63628, "device_end": 1585639562.637135}, "cmdq": 1, "read": {"device_start": -1, "device_end": -1}}, "FFC_sans_bias79": {"write": {"device_start": 1585639562.6441092, "host_queued_start": 1585639629.520502, "device_queued": 1585639562.6376874, "device_end": 1585639562.6441402, "host_queued_end": 1585639629.520605}, "device": "gpu", "nd_range": {"device_start": 1585639562.6441438, "device_end": 1585639562.644902}, "cmdq": 2, "read": {"device_start": 1585639562.6449082, "device_end": 1585639562.644931}}, "FFC_sans_bias56": {"write": {"device_start": 1585639562.6360917, "host_queued_start": 1585639629.50516, "device_queued": 1585639562.635814, "device_end": 1585639562.636117, "host_queued_end": 1585639629.520605}, "device": "gpu", "nd_range": {"device_start": 1585639562.63612, "device_end": 1585639562.6367254}, "cmdq": 0, "read": {"device_start": -1, "device_end": -1}}, "FFC_sans_bias51": {"write": {"device_start": -1, "host_queued_start": 1585639629.55483, "device_queued": -1, "device_end": -1, "host_queued_end": 1585639629.560889}, "device": "cpu", "nd_range": {"device_start": 2307403.864261678, "device_end": 2307403.8795473673}, "cmdq": 3, "read": {"device_start": -1, "device_end": -1}}, "softmax23": {"write": {"device_start": -1, "host_queued_start": 1585639629.551908, "device_queued": -1, "device_end": -1, "host_queued_end": 1585639629.560889}, "device": "cpu", "nd_range": {"device_start": 2307403.864797473, "device_end": 2307403.865003011}, "cmdq": 2, "read": {"device_start": -1, "device_end": -1}}, "FFC_sans_bias37": {"write": {"device_start": -1, "host_queued_start": 1585639629.541777, "device_queued": -1, "device_end": -1, "host_queued_end": 1585639629.560889}, "device": "cpu", "nd_range": {"device_start": 2307403.797066531, "device_end": 2307403.812300535}, "cmdq": 3, "read": {"device_start": -1, "device_end": -1}}, "FFC_sans_bias73": {"write": {"device_start": 1585639562.638757, "host_queued_start": 1585639629.512538, "device_queued": 1585639562.6367126, "device_end": 1585639562.638789, "host_queued_end": 1585639629.520605}, "device": "gpu", "nd_range": {"device_start": 1585639562.638795, "device_end": 1585639562.6401143}, "cmdq": 1, "read": {"device_start": -1, "device_end": -1}}, "empty62": {"write": {"device_start": 1585639562.635771, "host_queued_start": 1585639629.502176, "device_queued": 1585639562.6356297, "device_end": 1585639562.6358223, "host_queued_end": 1585639629.520605}, "device": "gpu", "nd_range": {"device_start": 1585639562.6358287, "device_end": 1585639562.635842}, "cmdq": 0, "read": {"device_start": -1, "device_end": -1}}, "FFC_sans_bias70": {"write": {"device_start": 1585639562.6431587, "host_queued_start": 1585639629.519455, "device_queued": 1585639562.6375546, "device_end": 1585639562.6431901, "host_queued_end": 1585639629.520605}, "device": "gpu", "nd_range": {"device_start": 1585639562.643193, "device_end": 1585639562.6444495}, "cmdq": 1, "read": {"device_start": 1585639562.6444547, "device_end": 1585639562.6444788}}, "FFC_sans_bias58": {"write": {"device_start": -1, "host_queued_start": 1585639629.514903, "device_queued": -1, "device_end": -1, "host_queued_end": 1585639629.520605}, "device": "gpu", "nd_range": {"device_start": 1585639562.6404557, "device_end": 1585639562.6410599}, "cmdq": 0, "read": {"device_start": -1, "device_end": -1}}, "softmax41": {"write": {"device_start": -1, "host_queued_start": 1585639629.552453, "device_queued": -1, "device_end": -1, "host_queued_end": 1585639629.560889}, "device": "cpu", "nd_range": {"device_start": 2307403.8722112873, "device_end": 2307403.872421008}, "cmdq": 0, "read": {"device_start": -1, "device_end": -1}}, "FFC_sans_bias74": {"write": {"device_start": 1585639562.6392455, "host_queued_start": 1585639629.513613, "device_queued": 1585639562.6367483, "device_end": 1585639562.6392775, "host_queued_end": 1585639629.520605}, "device": "gpu", "nd_range": {"device_start": 1585639562.6392827, "device_end": 1585639562.6405718}, "cmdq": 2, "read": {"device_start": -1, "device_end": -1}}, "FFC_sans_bias11": {"write": {"device_start": -1, "host_queued_start": 1585639629.53335, "device_queued": -1, "device_end": -1, "host_queued_end": 1585639629.560889}, "device": "cpu", "nd_range": {"device_start": 2307403.7665112633, "device_end": 2307403.781767329}, "cmdq": 3, "read": {"device_start": -1, "device_end": -1}}, "FFC_sans_bias10": {"write": {"device_start": -1, "host_queued_start": 1585639629.532282, "device_queued": -1, "device_end": -1, "host_queued_end": 1585639629.560889}, "device": "cpu", "nd_range": {"device_start": 2307403.767216864, "device_end": 2307403.7834900334}, "cmdq": 2, "read": {"device_start": -1, "device_end": -1}}, "coalesced_transpose3": {"write": {"device_start": -1, "host_queued_start": 1585639629.54638, "device_queued": -1, "device_end": -1, "host_queued_end": 1585639629.560889}, "device": "cpu", "nd_range": {"device_start": 2307403.8416308532, "device_end": 2307403.8418782903}, "cmdq": 0, "read": {"device_start": -1, "device_end": -1}}, "FFC_sans_bias34": {"write": {"device_start": -1, "host_queued_start": 1585639629.558855, "device_queued": -1, "device_end": -1, "host_queued_end": 1585639629.560889}, "device": "cpu", "nd_range": {"device_start": 2307403.879556414, "device_end": 2307403.8948486513}, "cmdq": 3, "read": {"device_start": -1, "device_end": -1}}, "FFC_sans_bias15": {"write": {"device_start": -1, "host_queued_start": 1585639629.553399, "device_queued": -1, "device_end": -1, "host_queued_end": 1585639629.560889}, "device": "cpu", "nd_range": {"device_start": 2307403.847916161, "device_end": 2307403.864250896}, "cmdq": 3, "read": {"device_start": -1, "device_end": -1}}, "FFC_sans_bias31": {"write": {"device_start": -1, "host_queued_start": 1585639629.549458, "device_queued": -1, "device_end": -1, "host_queued_end": 1585639629.560889}, "device": "cpu", "nd_range": {"device_start": 2307403.827855064, "device_end": 2307403.841457126}, "cmdq": 1, "read": {"device_start": -1, "device_end": -1}}, "FFC_sans_bias16": {"write": {"device_start": -1, "host_queued_start": 1585639629.556866, "device_queued": -1, "device_end": -1, "host_queued_end": 1585639629.560889}, "device": "cpu", "nd_range": {"device_start": 2307403.86444895, "device_end": 2307403.880713292}, "cmdq": 1, "read": {"device_start": -1, "device_end": -1}}, "FFC_sans_bias19": {"write": {"device_start": -1, "host_queued_start": 1585639629.535456, "device_queued": -1, "device_end": -1, "host_queued_end": 1585639629.560889}, "device": "cpu", "nd_range": {"device_start": 2307403.765809659, "device_end": 2307403.780965264}, "cmdq": 1, "read": {"device_start": -1, "device_end": -1}}, "FFC_sans_bias18": {"write": {"device_start": -1, "host_queued_start": 1585639629.534391, "device_queued": -1, "device_end": -1, "host_queued_end": 1585639629.560889}, "device": "cpu", "nd_range": {"device_start": 2307403.769497076, "device_end": 2307403.791205565}, "cmdq": 0, "read": {"device_start": -1, "device_end": -1}}, "coalesced_transpose30": {"write": {"device_start": -1, "host_queued_start": 1585639629.547391, "device_queued": -1, "device_end": -1, "host_queued_end": 1585639629.560889}, "device": "cpu", "nd_range": {"device_start": 2307403.826820537, "device_end": 2307403.827062734}, "cmdq": 3, "read": {"device_start": -1, "device_end": -1}}, "empty80": {"write": {"device_start": 1585639562.6359982, "host_queued_start": 1585639629.504158, "device_queued": 1585639562.6357415, "device_end": 1585639562.636067, "host_queued_end": 1585639629.520605}, "device": "gpu", "nd_range": {"device_start": 1585639562.6360736, "device_end": 1585639562.6360781}, "cmdq": 2, "read": {"device_start": -1, "device_end": -1}}, "FFC_sans_bias69": {"write": {"device_start": -1, "host_queued_start": 1585639629.517021, "device_queued": -1, "device_end": -1, "host_queued_end": 1585639629.520605}, "device": "gpu", "nd_range": {"device_start": 1585639562.6422124, "device_end": 1585639562.6430285}, "cmdq": 1, "read": {"device_start": -1, "device_end": -1}}, "FFC_sans_bias38": {"write": {"device_start": -1, "host_queued_start": 1585639629.542858, "device_queued": -1, "device_end": -1, "host_queued_end": 1585639629.560889}, "device": "cpu", "nd_range": {"device_start": 2307403.822875165, "device_end": 2307403.841324368}, "cmdq": 0, "read": {"device_start": -1, "device_end": -1}}, "coalesced_transpose57": {"write": {"device_start": -1, "host_queued_start": 1585639629.513944, "device_queued": -1, "device_end": -1, "host_queued_end": 1585639629.520605}, "device": "gpu", "nd_range": {"device_start": 1585639562.6395948, "device_end": 1585639562.6404548}, "cmdq": 0, "read": {"device_start": -1, "device_end": -1}}, "FFC_sans_bias76": {"write": {"device_start": -1, "host_queued_start": 1585639629.515535, "device_queued": -1, "device_end": -1, "host_queued_end": 1585639629.520605}, "device": "gpu", "nd_range": {"device_start": 1585639562.641429, "device_end": 1585639562.6420367}, "cmdq": 2, "read": {"device_start": -1, "device_end": -1}}, "coalesced_transpose75": {"write": {"device_start": -1, "host_queued_start": 1585639629.514544, "device_queued": -1, "device_end": -1, "host_queued_end": 1585639629.520605}, "device": "gpu", "nd_range": {"device_start": 1585639562.6405787, "device_end": 1585639562.6414278}, "cmdq": 2, "read": {"device_start": -1, "device_end": -1}}, "empty26": {"write": {"device_start": -1, "host_queued_start": 1585639629.524191, "device_queued": -1, "device_end": -1, "host_queued_end": 1585639629.560889}, "device": "cpu", "nd_range": {"device_start": 2307403.750538721, "device_end": 2307403.750543125}, "cmdq": 2, "read": {"device_start": -1, "device_end": -1}}, "softmax77": {"write": {"device_start": -1, "host_queued_start": 1585639629.516285, "device_queued": -1, "device_end": -1, "host_queued_end": 1585639629.520605}, "device": "gpu", "nd_range": {"device_start": 1585639562.6420379, "device_end": 1585639562.6426957}, "cmdq": 2, "read": {"device_start": -1, "device_end": -1}}, "coalesced_transpose12": {"write": {"device_start": -1, "host_queued_start": 1585639629.546722, "device_queued": -1, "device_end": -1, "host_queued_end": 1585639629.560889}, "device": "cpu", "nd_range": {"device_start": 2307403.811804316, "device_end": 2307403.812061747}, "cmdq": 1, "read": {"device_start": -1, "device_end": -1}}, "empty44": {"write": {"device_start": -1, "host_queued_start": 1585639629.525977, "device_queued": -1, "device_end": -1, "host_queued_end": 1585639629.560889}, "device": "cpu", "nd_range": {"device_start": 2307403.750524699, "device_end": 2307403.750526123}, "cmdq": 0, "read": {"device_start": -1, "device_end": -1}}, "coalesced_transpose21": {"write": {"device_start": -1, "host_queued_start": 1585639629.547057, "device_queued": -1, "device_end": -1, "host_queued_end": 1585639629.560889}, "device": "cpu", "nd_range": {"device_start": 2307403.823916606, "device_end": 2307403.824170527}, "cmdq": 2, "read": {"device_start": -1, "device_end": -1}}, "FFC_sans_bias36": {"write": {"device_start": -1, "host_queued_start": 1585639629.540732, "device_queued": -1, "device_end": -1, "host_queued_end": 1585639629.560889}, "device": "cpu", "nd_range": {"device_start": 2307403.798933417, "device_end": 2307403.8152037133}, "cmdq": 2, "read": {"device_start": -1, "device_end": -1}}, "softmax14": {"write": {"device_start": -1, "host_queued_start": 1585639629.551637, "device_queued": -1, "device_end": -1, "host_queued_end": 1585639629.560889}, "device": "cpu", "nd_range": {"device_start": 2307403.8415757073, "device_end": 2307403.8417896084}, "cmdq": 1, "read": {"device_start": -1, "device_end": -1}}, "FFC_sans_bias13": {"write": {"device_start": -1, "host_queued_start": 1585639629.548751, "device_queued": -1, "device_end": -1, "host_queued_end": 1585639629.560889}, "device": "cpu", "nd_range": {"device_start": 2307403.827175836, "device_end": 2307403.8376337374}, "cmdq": 3, "read": {"device_start": -1, "device_end": -1}}, "empty8": {"write": {"device_start": -1, "host_queued_start": 1585639629.522038, "device_queued": -1, "device_end": -1, "host_queued_end": 1585639629.560889}, "device": "cpu", "nd_range": {"device_start": 2307403.750491721, "device_end": 2307403.750502656}, "cmdq": 0, "read": {"device_start": -1, "device_end": -1}}, "FFC_sans_bias42": {"write": {"device_start": -1, "host_queued_start": 1585639629.554458, "device_queued": -1, "device_end": -1, "host_queued_end": 1585639629.560889}, "device": "cpu", "nd_range": {"device_start": 2307403.880679294, "device_end": 2307403.8965467904}, "cmdq": 2, "read": {"device_start": -1, "device_end": -1}}, "FFC_sans_bias43": {"write": {"device_start": -1, "host_queued_start": 1585639629.55985, "device_queued": -1, "device_end": -1, "host_queued_end": 1585639629.560889}, "device": "cpu", "nd_range": {"device_start": 2307403.903882864, "device_end": 2307403.911236767}, "cmdq": 0, "read": {"device_start": -1, "device_end": -1}}, "FFC_sans_bias40": {"write": {"device_start": -1, "host_queued_start": 1585639629.550729, "device_queued": -1, "device_end": -1, "host_queued_end": 1585639629.560889}, "device": "cpu", "nd_range": {"device_start": 2307403.8494109213, "device_end": 2307403.8645945713}, "cmdq": 2, "read": {"device_start": -1, "device_end": -1}}, "softmax32": {"write": {"device_start": -1, "host_queued_start": 1585639629.552179, "device_queued": -1, "device_end": -1, "host_queued_end": 1585639629.560889}, "device": "cpu", "nd_range": {"device_start": 2307403.847599136, "device_end": 2307403.8478099653}, "cmdq": 3, "read": {"device_start": -1, "device_end": -1}}, "FFC_sans_bias47": {"write": {"device_start": -1, "host_queued_start": 1585639629.546047, "device_queued": -1, "device_end": -1, "host_queued_end": 1585639629.560889}, "device": "cpu", "nd_range": {"device_start": 2307403.812417978, "device_end": 2307403.826708584}, "cmdq": 3, "read": {"device_start": -1, "device_end": -1}}, "FFC_sans_bias78": {"write": {"device_start": -1, "host_queued_start": 1585639629.517369, "device_queued": -1, "device_end": -1, "host_queued_end": 1585639629.520605}, "device": "gpu", "nd_range": {"device_start": 1585639562.6426969, "device_end": 1585639562.643985}, "cmdq": 2, "read": {"device_start": -1, "device_end": -1}}, "FFC_sans_bias45": {"write": {"device_start": -1, "host_queued_start": 1585639629.543909, "device_queued": -1, "device_end": -1, "host_queued_end": 1585639629.560889}, "device": "cpu", "nd_range": {"device_start": 2307403.7963625863, "device_end": 2307403.811660265}, "cmdq": 1, "read": {"device_start": -1, "device_end": -1}}, "softmax50": {"write": {"device_start": -1, "host_queued_start": 1585639629.552725, "device_queued": -1, "device_end": -1, "host_queued_end": 1585639629.560889}, "device": "cpu", "nd_range": {"device_start": 2307403.8487309422, "device_end": 2307403.8489396484}, "cmdq": 1, "read": {"device_start": -1, "device_end": -1}}, "FFC_sans_bias33": {"write": {"device_start": -1, "host_queued_start": 1585639629.554113, "device_queued": -1, "device_end": -1, "host_queued_end": 1585639629.560889}, "device": "cpu", "nd_range": {"device_start": 2307403.849064955, "device_end": 2307403.8614867763}, "cmdq": 1, "read": {"device_start": -1, "device_end": -1}}, "FFC_sans_bias63": {"write": {"device_start": 1585639562.6378222, "host_queued_start": 1585639629.510404, "device_queued": 1585639562.6364946, "device_end": 1585639562.6378543, "host_queued_end": 1585639629.520605}, "device": "gpu", "nd_range": {"device_start": 1585639562.6378596, "device_end": 1585639562.6391222}, "cmdq": 2, "read": {"device_start": -1, "device_end": -1}}, "FFC_sans_bias49": {"write": {"device_start": -1, "host_queued_start": 1585639629.551082, "device_queued": -1, "device_end": -1, "host_queued_end": 1585639629.560889}, "device": "cpu", "nd_range": {"device_start": 2307403.8376415703, "device_end": 2307403.8474795823}, "cmdq": 3, "read": {"device_start": -1, "device_end": -1}}, "FFC_sans_bias64": {"write": {"device_start": 1585639562.6368294, "host_queued_start": 1585639629.508332, "device_queued": 1585639562.63632, "device_end": 1585639562.636854, "host_queued_end": 1585639629.520605}, "device": "gpu", "nd_range": {"device_start": 1585639562.636859, "device_end": 1585639562.638127}, "cmdq": 0, "read": {"device_start": -1, "device_end": -1}}, "FFC_sans_bias65": {"write": {"device_start": 1585639562.6372685, "host_queued_start": 1585639629.509368, "device_queued": 1585639562.6363616, "device_end": 1585639562.6372988, "host_queued_end": 1585639629.520605}, "device": "gpu", "nd_range": {"device_start": 1585639562.6373022, "device_end": 1585639562.6386468}, "cmdq": 1, "read": {"device_start": -1, "device_end": -1}}, "FFC_sans_bias72": {"write": {"device_start": 1585639562.6382554, "host_queued_start": 1585639629.511479, "device_queued": 1585639562.636559, "device_end": 1585639562.6382868, "host_queued_end": 1585639629.520605}, "device": "gpu", "nd_range": {"device_start": 1585639562.6382916, "device_end": 1585639562.6395931}, "cmdq": 0, "read": {"device_start": -1, "device_end": -1}}, "FFC_sans_bias67": {"write": {"device_start": -1, "host_queued_start": 1585639629.515219, "device_queued": -1, "device_end": -1, "host_queued_end": 1585639629.520605}, "device": "gpu", "nd_range": {"device_start": 1585639562.6404648, "device_end": 1585639562.6415412}, "cmdq": 1, "read": {"device_start": -1, "device_end": -1}}, "FFC_sans_bias24": {"write": {"device_start": -1, "host_queued_start": 1585639629.553773, "device_queued": -1, "device_end": -1, "host_queued_end": 1585639629.560889}, "device": "cpu", "nd_range": {"device_start": 2307403.8724284703, "device_end": 2307403.8877469813}, "cmdq": 0, "read": {"device_start": -1, "device_end": -1}}, "FFC_sans_bias25": {"write": {"device_start": -1, "host_queued_start": 1585639629.557856, "device_queued": -1, "device_end": -1, "host_queued_end": 1585639629.560889}, "device": "cpu", "nd_range": {"device_start": 2307403.896667656, "device_end": 2307403.905497893}, "cmdq": 2, "read": {"device_start": -1, "device_end": -1}}, "FFC_sans_bias27": {"write": {"device_start": -1, "host_queued_start": 1585639629.537554, "device_queued": -1, "device_end": -1, "host_queued_end": 1585639629.560889}, "device": "cpu", "nd_range": {"device_start": 2307403.7817755803, "device_end": 2307403.796949876}, "cmdq": 3, "read": {"device_start": -1, "device_end": -1}}, "FFC_sans_bias20": {"write": {"device_start": -1, "host_queued_start": 1585639629.53651, "device_queued": -1, "device_end": -1, "host_queued_end": 1585639629.560889}, "device": "cpu", "nd_range": {"device_start": 2307403.783604857, "device_end": 2307403.798819913}, "cmdq": 2, "read": {"device_start": -1, "device_end": -1}}, "FFC_sans_bias22": {"write": {"device_start": -1, "host_queued_start": 1585639629.549113, "device_queued": -1, "device_end": -1, "host_queued_end": 1585639629.560889}, "device": "cpu", "nd_range": {"device_start": 2307403.843719718, "device_end": 2307403.8643910233}, "cmdq": 0, "read": {"device_start": -1, "device_end": -1}}, "softmax68": {"write": {"device_start": -1, "host_queued_start": 1585639629.516039, "device_queued": -1, "device_end": -1, "host_queued_end": 1585639629.520605}, "device": "gpu", "nd_range": {"device_start": 1585639562.6415422, "device_end": 1585639562.6422114}, "cmdq": 1, "read": {"device_start": -1, "device_end": -1}}, "softmax5": {"write": {"device_start": -1, "host_queued_start": 1585639629.551363, "device_queued": -1, "device_end": -1, "host_queued_end": 1585639629.560889}, "device": "cpu", "nd_range": {"device_start": 2307403.864400161, "device_end": 2307403.8646128643}, "cmdq": 0, "read": {"device_start": -1, "device_end": -1}}, "FFC_sans_bias28": {"write": {"device_start": -1, "host_queued_start": 1585639629.538627, "device_queued": -1, "device_end": -1, "host_queued_end": 1585639629.560889}, "device": "cpu", "nd_range": {"device_start": 2307403.8000210263, "device_end": 2307403.8193694}, "cmdq": 0, "read": {"device_start": -1, "device_end": -1}}, "FFC_sans_bias29": {"write": {"device_start": -1, "host_queued_start": 1585639629.539685, "device_queued": -1, "device_end": -1, "host_queued_end": 1585639629.560889}, "device": "cpu", "nd_range": {"device_start": 2307403.781106104, "device_end": 2307403.796239341}, "cmdq": 1, "read": {"device_start": -1, "device_end": -1}}, "empty17": {"write": {"device_start": -1, "host_queued_start": 1585639629.523158, "device_queued": -1, "device_end": -1, "host_queued_end": 1585639629.560889}, "device": "cpu", "nd_range": {"device_start": 2307403.750492886, "device_end": 2307403.750502596}, "cmdq": 1, "read": {"device_start": -1, "device_end": -1}}, "softmax59": {"write": {"device_start": -1, "host_queued_start": 1585639629.515793, "device_queued": -1, "device_end": -1, "host_queued_end": 1585639629.520605}, "device": "gpu", "nd_range": {"device_start": 1585639562.6410613, "device_end": 1585639562.6417742}, "cmdq": 0, "read": {"device_start": -1, "device_end": -1}}, "empty71": {"write": {"device_start": 1585639562.6358933, "host_queued_start": 1585639629.503253, "device_queued": 1585639562.6357207, "device_end": 1585639562.6359556, "host_queued_end": 1585639629.520605}, "device": "gpu", "nd_range": {"device_start": 1585639562.6359606, "device_end": 1585639562.6359713}, "cmdq": 1, "read": {"device_start": -1, "device_end": -1}}, "empty35": {"write": {"device_start": -1, "host_queued_start": 1585639629.525152, "device_queued": -1, "device_end": -1, "host_queued_end": 1585639629.560889}, "device": "cpu", "nd_range": {"device_start": 2307403.750774302, "device_end": 2307403.750777883}, "cmdq": 3, "read": {"device_start": -1, "device_end": -1}}, "empty53": {"write": {"device_start": -1, "host_queued_start": 1585639629.526805, "device_queued": -1, "device_end": -1, "host_queued_end": 1585639629.560889}, "device": "cpu", "nd_range": {"device_start": 2307403.750524926, "device_end": 2307403.750526003}, "cmdq": 1, "read": {"device_start": -1, "device_end": -1}}, "FFC_sans_bias46": {"write": {"device_start": -1, "host_queued_start": 1585639629.544978, "device_queued": -1, "device_end": -1, "host_queued_end": 1585639629.560889}, "device": "cpu", "nd_range": {"device_start": 2307403.815327472, "device_end": 2307403.823793158}, "cmdq": 2, "read": {"device_start": -1, "device_end": -1}}, "coalesced_transpose66": {"write": {"device_start": -1, "host_queued_start": 1585639629.514248, "device_queued": -1, "device_end": -1, "host_queued_end": 1585639629.520605}, "device": "gpu", "nd_range": {"device_start": 1585639562.640117, "device_end": 1585639562.640463}, "cmdq": 1, "read": {"device_start": -1, "device_end": -1}}, "coalesced_transpose48": {"write": {"device_start": -1, "host_queued_start": 1585639629.548056, "device_queued": -1, "device_end": -1, "host_queued_end": 1585639629.560889}, "device": "cpu", "nd_range": {"device_start": 2307403.824280872, "device_end": 2307403.824512795}, "cmdq": 1, "read": {"device_start": -1, "device_end": -1}}}