{"FFC_sans_bias4": {"write": {"device_start": -1, "host_queued_start": 1585619724.758517, "device_queued": -1, "device_end": -1, "host_queued_end": 1585619724.760436}, "device": "cpu", "nd_range": {"device_start": 2287498.961457516, "device_end": 2287498.9657191103}, "cmdq": 1, "read": {"device_start": -1, "device_end": -1}}, "FFC_sans_bias7": {"write": {"device_start": -1, "host_queued_start": 1585619724.760383, "device_queued": -1, "device_end": -1, "host_queued_end": 1585619724.760436}, "device": "cpu", "nd_range": {"device_start": 2287498.9709949093, "device_end": 2287498.975315166}, "cmdq": 0, "read": {"device_start": -1, "device_end": -1}}, "FFC_sans_bias6": {"write": {"device_start": -1, "host_queued_start": 1585619724.759222, "device_queued": -1, "device_end": -1, "host_queued_end": 1585619724.760436}, "device": "cpu", "nd_range": {"device_start": 2287498.9660134683, "device_end": 2287498.970870716}, "cmdq": 3, "read": {"device_start": -1, "device_end": -1}}, "FFC_sans_bias1": {"write": {"device_start": -1, "host_queued_start": 1585619724.756649, "device_queued": -1, "device_end": -1, "host_queued_end": 1585619724.760436}, "device": "cpu", "nd_range": {"device_start": 2287498.9500510483, "device_end": 2287498.958624366}, "cmdq": 2, "read": {"device_start": -1, "device_end": -1}}, "FFC_sans_bias0": {"write": {"device_start": -1, "host_queued_start": 1585619724.755497, "device_queued": -1, "device_end": -1, "host_queued_end": 1585619724.760436}, "device": "cpu", "nd_range": {"device_start": 2287498.950034105, "device_end": 2287498.9613312082}, "cmdq": 1, "read": {"device_start": -1, "device_end": -1}}, "FFC_sans_bias2": {"write": {"device_start": -1, "host_queued_start": 1585619724.75775, "device_queued": -1, "device_end": -1, "host_queued_end": 1585619724.760436}, "device": "cpu", "nd_range": {"device_start": 2287498.950044582, "device_end": 2287498.961913288}, "cmdq": 3, "read": {"device_start": -1, "device_end": -1}}, "FFC_sans_bias9": {"write": {"device_start": 1585619658.410744, "host_queued_start": 1585619724.742733, "device_queued": 1585619658.4105442, "device_end": 1585619658.410769, "host_queued_end": 1585619724.752875}, "device": "gpu", "nd_range": {"device_start": 1585619658.4107778, "device_end": 1585619658.4113855}, "cmdq": 2, "read": {"device_start": -1, "device_end": -1}}, "softmax23": {"write": {"device_start": -1, "host_queued_start": 1585619724.749851, "device_queued": -1, "device_end": -1, "host_queued_end": 1585619724.752875}, "device": "gpu", "nd_range": {"device_start": 1585619658.4147816, "device_end": 1585619658.4149804}, "cmdq": 1, "read": {"device_start": -1, "device_end": -1}}, "FFC_sans_bias11": {"write": {"device_start": 1585619658.4109888, "host_queued_start": 1585619724.744857, "device_queued": 1585619658.4108346, "device_end": 1585619658.4110193, "host_queued_end": 1585619724.752875}, "device": "gpu", "nd_range": {"device_start": 1585619658.4110236, "device_end": 1585619658.412372}, "cmdq": 1, "read": {"device_start": -1, "device_end": -1}}, "FFC_sans_bias10": {"write": {"device_start": 1585619658.4108875, "host_queued_start": 1585619724.743813, "device_queued": 1585619658.4107854, "device_end": 1585619658.410955, "host_queued_end": 1585619724.752875}, "device": "gpu", "nd_range": {"device_start": 1585619658.410959, "device_end": 1585619658.4117908}, "cmdq": 0, "read": {"device_start": -1, "device_end": -1}}, "coalesced_transpose3": {"write": {"device_start": -1, "host_queued_start": 1585619724.758158, "device_queued": -1, "device_end": -1, "host_queued_end": 1585619724.760436}, "device": "cpu", "nd_range": {"device_start": 2287498.959588792, "device_end": 2287498.959824745}, "cmdq": 0, "read": {"device_start": -1, "device_end": -1}}, "FFC_sans_bias15": {"write": {"device_start": -1, "host_queued_start": 1585619724.750161, "device_queued": -1, "device_end": -1, "host_queued_end": 1585619724.752875}, "device": "gpu", "nd_range": {"device_start": 1585619658.4149864, "device_end": 1585619658.4155843}, "cmdq": 2, "read": {"device_start": -1, "device_end": -1}}, "FFC_sans_bias16": {"write": {"device_start": 1585619658.4158363, "host_queued_start": 1585619724.751716, "device_queued": 1585619658.4116418, "device_end": 1585619658.4158661, "host_queued_end": 1585619724.752875}, "device": "gpu", "nd_range": {"device_start": 1585619658.4158716, "device_end": 1585619658.4166026}, "cmdq": 1, "read": {"device_start": 1585619658.4166086, "device_end": 1585619658.4166322}}, "FFC_sans_bias19": {"write": {"device_start": 1585619658.4118888, "host_queued_start": 1585619724.746989, "device_queued": 1585619658.411051, "device_end": 1585619658.4119198, "host_queued_end": 1585619724.752875}, "device": "gpu", "nd_range": {"device_start": 1585619658.4119241, "device_end": 1585619658.4133365}, "cmdq": 0, "read": {"device_start": -1, "device_end": -1}}, "FFC_sans_bias18": {"write": {"device_start": 1585619658.4115012, "host_queued_start": 1585619724.745895, "device_queued": 1585619658.410851, "device_end": 1585619658.4115262, "host_queued_end": 1585619724.752875}, "device": "gpu", "nd_range": {"device_start": 1585619658.4115303, "device_end": 1585619658.4127846}, "cmdq": 2, "read": {"device_start": -1, "device_end": -1}}, "empty26": {"write": {"device_start": 1585619658.4106462, "host_queued_start": 1585619724.741679, "device_queued": 1585619658.4105146, "device_end": 1585619658.4107156, "host_queued_end": 1585619724.752875}, "device": "gpu", "nd_range": {"device_start": 1585619658.4107199, "device_end": 1585619658.4107237}, "cmdq": 1, "read": {"device_start": -1, "device_end": -1}}, "coalesced_transpose12": {"write": {"device_start": -1, "host_queued_start": 1585619724.748364, "device_queued": -1, "device_end": -1, "host_queued_end": 1585619724.752875}, "device": "gpu", "nd_range": {"device_start": 1585619658.4127858, "device_end": 1585619658.4136121}, "cmdq": 2, "read": {"device_start": -1, "device_end": -1}}, "coalesced_transpose21": {"write": {"device_start": -1, "host_queued_start": 1585619724.748687, "device_queued": -1, "device_end": -1, "host_queued_end": 1585619724.752875}, "device": "gpu", "nd_range": {"device_start": 1585619658.4133375, "device_end": 1585619658.4136317}, "cmdq": 0, "read": {"device_start": -1, "device_end": -1}}, "softmax14": {"write": {"device_start": -1, "host_queued_start": 1585619724.749595, "device_queued": -1, "device_end": -1, "host_queued_end": 1585619724.752875}, "device": "gpu", "nd_range": {"device_start": 1585619658.4147775, "device_end": 1585619658.4149783}, "cmdq": 0, "read": {"device_start": -1, "device_end": -1}}, "FFC_sans_bias13": {"write": {"device_start": -1, "host_queued_start": 1585619724.749015, "device_queued": -1, "device_end": -1, "host_queued_end": 1585619724.752875}, "device": "gpu", "nd_range": {"device_start": 1585619658.4137673, "device_end": 1585619658.4143648}, "cmdq": 1, "read": {"device_start": -1, "device_end": -1}}, "empty8": {"write": {"device_start": -1, "host_queued_start": 1585619724.754258, "device_queued": -1, "device_end": -1, "host_queued_end": 1585619724.760436}, "device": "cpu", "nd_range": {"device_start": 2287498.950010106, "device_end": 2287498.950022185}, "cmdq": 0, "read": {"device_start": -1, "device_end": -1}}, "FFC_sans_bias24": {"write": {"device_start": -1, "host_queued_start": 1585619724.750672, "device_queued": -1, "device_end": -1, "host_queued_end": 1585619724.752875}, "device": "gpu", "nd_range": {"device_start": 1585619658.4155884, "device_end": 1585619658.416196}, "cmdq": 0, "read": {"device_start": -1, "device_end": -1}}, "FFC_sans_bias25": {"write": {"device_start": 1585619658.4157498, "host_queued_start": 1585619724.752771, "device_queued": 1585619658.4116066, "device_end": 1585619658.415812, "host_queued_end": 1585619724.752875}, "device": "gpu", "nd_range": {"device_start": 1585619658.4162009, "device_end": 1585619658.4171565}, "cmdq": 2, "read": {"device_start": 1585619658.417158, "device_end": 1585619658.4171817}}, "FFC_sans_bias20": {"write": {"device_start": 1585619658.412501, "host_queued_start": 1585619724.748035, "device_queued": 1585619658.4111922, "device_end": 1585619658.4125323, "host_queued_end": 1585619724.752875}, "device": "gpu", "nd_range": {"device_start": 1585619658.4125366, "device_end": 1585619658.4137564}, "cmdq": 1, "read": {"device_start": -1, "device_end": -1}}, "FFC_sans_bias22": {"write": {"device_start": -1, "host_queued_start": 1585619724.749337, "device_queued": -1, "device_end": -1, "host_queued_end": 1585619724.752875}, "device": "gpu", "nd_range": {"device_start": 1585619658.413774, "device_end": 1585619658.4147713}, "cmdq": 2, "read": {"device_start": -1, "device_end": -1}}, "softmax5": {"write": {"device_start": -1, "host_queued_start": 1585619724.758877, "device_queued": -1, "device_end": -1, "host_queued_end": 1585619724.760436}, "device": "cpu", "nd_range": {"device_start": 2287498.965725957, "device_end": 2287498.965863923}, "cmdq": 2, "read": {"device_start": -1, "device_end": -1}}, "empty17": {"write": {"device_start": 1585619658.4105327, "host_queued_start": 1585619724.740638, "device_queued": 1585619658.410419, "device_end": 1585619658.4105837, "host_queued_end": 1585619724.752875}, "device": "gpu", "nd_range": {"device_start": 1585619658.410591, "device_end": 1585619658.4106028}, "cmdq": 0, "read": {"device_start": -1, "device_end": -1}}}